onqlave/__init__.py
onqlave/connection/__init__.py
onqlave/connection/client.py
onqlave/connection/connection.py
onqlave/contracts/__init__.py
onqlave/contracts/contracts.py
onqlave/contracts/requests/__init__.py
onqlave/contracts/requests/requests.py
onqlave/contracts/responses/__init__.py
onqlave/contracts/responses/responses.py
onqlave/credentials/__init__.py
onqlave/credentials/credentials.py
onqlave/encryption/__init__.py
onqlave/encryption/encrypted_stream_processor.py
onqlave/encryption/encryption.py
onqlave/encryption/options.py
onqlave/encryption/plain_stream_processor.py
onqlave/errors/__init__.py
onqlave/errors/errors.py
onqlave/keymanager/__init__.py
onqlave/keymanager/id_service.py
onqlave/keymanager/key_manager_client.py
onqlave/keymanager/random_service.py
onqlave/keymanager/factories/__init__.py
onqlave/keymanager/factories/aes_gcm_factory.py
onqlave/keymanager/factories/rsa_ssa_pkcs1_sha_factory.py
onqlave/keymanager/factories/xchacha20_poly1305_factory.py
onqlave/keymanager/keys/__init__.py
onqlave/keymanager/keys/aes_gcm.py
onqlave/keymanager/keys/xchacha_20_poly_1350.py
onqlave/keymanager/onqlave_types/__init__.py
onqlave/keymanager/onqlave_types/types.py
onqlave/keymanager/operations/__init__.py
onqlave/keymanager/operations/aes_128_gcm_operation.py
onqlave/keymanager/operations/aes_256_gcm_operation.py
onqlave/keymanager/operations/rsa_ssa_pkcs1_sha_operation.py
onqlave/keymanager/operations/xchacha20_poly1305_operation.py
onqlave/keymanager/primitives/__init__.py
onqlave/keymanager/primitives/aes_gcm_aead.py
onqlave/keymanager/primitives/rsa_ssa_pkcs1_sha.py
onqlave/keymanager/primitives/xchacha20_poly1305_aead.py
onqlave/logger/__init__.py
onqlave/logger/logger.py
onqlave/messages/__init__.py
onqlave/messages/messages.py
onqlave/test/__init__.py
onqlave/test/hasher_test.py
onqlave/test/master_test.py
onqlave/test/test_pem_decrypt.py
onqlave/utils/__init__.py
onqlave/utils/hasher.py
onqlave_python_sdk_pilot-0.0.21.dist-info/LICENSE
onqlave_python_sdk_pilot-0.0.21.dist-info/METADATA
onqlave_python_sdk_pilot-0.0.21.dist-info/WHEEL
onqlave_python_sdk_pilot-0.0.21.dist-info/top_level.txt
onqlave_python_sdk_pilot-0.0.21.dist-info/RECORD
