Metadata-Version: 2.1
Name: onqlave-python-sdk-pilot
Version: 0.0.21
Summary: This Python SDK is designed to help developers easily integrate Onqlave Encryption As A Service into their python backend.
Home-page: https://github.com/onqlavelabs/onqlave-python/tree/dev
Download-URL: https://pypi.org/project/onqlave-python-sdk-pilot/#history
Author: Onqlave Pty
Author-email: product@onqlave.com
Maintainer: DC
Maintainer-email: dc@onqlave.com
License: MIT
Project-URL: Home Page, https://www.onqlave.com/
Project-URL: Issue Tracker, https://github.com/onqlavelabs/onqlave-python/issues
Project-URL: Source Code, https://github.com/onqlavelabs/onqlave-python/tree/dev
Keywords: encryption,privacy,sdk
Classifier: Development Status :: 3 - Alpha
Classifier: Environment :: Console
Classifier: Intended Audience :: Developers
Classifier: License :: OSI Approved :: MIT License
Classifier: Operating System :: POSIX :: Linux
Classifier: Operating System :: MacOS :: MacOS X
Classifier: Operating System :: Microsoft :: Windows
Classifier: Programming Language :: Python :: 3.8
Classifier: Programming Language :: Python :: 3.9
Classifier: Programming Language :: Python :: 3.10
Classifier: Programming Language :: Python :: 3 :: Only
Classifier: Topic :: Security
License-File: LICENSE
Requires-Dist: attrs (==23.1.0)
Requires-Dist: bleach (==6.0.0)
Requires-Dist: build (==0.10.0)
Requires-Dist: certifi (==2023.5.7)
Requires-Dist: cffi (==1.15.1)
Requires-Dist: charset-normalizer (==3.1.0)
Requires-Dist: cryptography (==41.0.1)
Requires-Dist: docutils (==0.20.1)
Requires-Dist: frozenlist (==1.4.0)
Requires-Dist: idna (==3.4)
Requires-Dist: importlib-metadata (==6.7.0)
Requires-Dist: importlib-resources (==5.12.0)
Requires-Dist: jaraco-classes (==3.2.3)
Requires-Dist: jeepney (==0.8.0)
Requires-Dist: keyring (==24.2.0)
Requires-Dist: markdown-it-py (==3.0.0)
Requires-Dist: mdurl (==0.1.2)
Requires-Dist: more-itertools (==9.1.0)
Requires-Dist: multidict (==6.0.4)
Requires-Dist: packaging (==23.1)
Requires-Dist: pip (==23.1.2)
Requires-Dist: pkginfo (==1.9.6)
Requires-Dist: pyasn1 (==0.5.0)
Requires-Dist: pycparser (==2.21)
Requires-Dist: pycryptodome (==3.18.0)
Requires-Dist: pygments (==2.15.1)
Requires-Dist: pyproject-hooks (==1.0.0)
Requires-Dist: readme-renderer (==40.0)
Requires-Dist: requests (==2.31.0)
Requires-Dist: requests-toolbelt (==1.0.0)
Requires-Dist: rfc3986 (==2.0.0)
Requires-Dist: rich (==13.4.2)
Requires-Dist: rsa (==4.9)
Requires-Dist: secretstorage (==3.3.3)
Requires-Dist: setuptools (==67.8.0)
Requires-Dist: six (==1.16.0)
Requires-Dist: tomli (==2.0.1)
Requires-Dist: twine (==4.0.2)
Requires-Dist: typing-extensions (==4.7.1)
Requires-Dist: urllib3 (==2.0.3)
Requires-Dist: webencodings (==0.5.1)
Requires-Dist: wheel (==0.38.4)
Requires-Dist: yarl (==1.9.2)
Requires-Dist: zipp (==3.15.0)
